eprint/__init__.py
eprint/__main__.py
eprint/eprint.py
eprint/str.py
eprint/version.py
tests/test_version.py
eprint-0.0.5.dist-info/LICENSE
eprint-0.0.5.dist-info/METADATA
eprint-0.0.5.dist-info/WHEEL
eprint-0.0.5.dist-info/entry_points.txt
eprint-0.0.5.dist-info/top_level.txt
eprint-0.0.5.dist-info/RECORD
