Metadata-Version: 2.1
Name: eprint
Version: 0.0.5
Summary: Enhanched print() for Python
Home-page: https://github.com/joaompinto/eprint
Author: João Pinto
Author-email: lamego.pinto@gmail.com
License: MIT
Platform: UNKNOWN
Requires-Dist: colored (>=1.4.2)
